sigmas/__init__.py
sigmas/cli.py
sigmas/simulations/__init__.py
sigmas/simulations/donut_sim.py
sigmas/simulations/run_sim.py
sigmas/simulations/sim.py
sigmas/simulations/utils.py
sigmas/simulations/python/__init__.py
sigmas/simulations/python/check_headers.py
sigmas/simulations/python/check_sof_files.py
sigmas/simulations/python/compare_yaml_with_drld.py
sigmas/simulations/python/downloadPackages.py
sigmas/simulations/python/downloads.py
sigmas/simulations/python/generateSummary.py
sigmas/simulations/python/grabHeaders.py
sigmas/simulations/python/makeCalibPrototypes.py
sigmas/simulations/python/makeSOF.py
sigmas/simulations/python/raw_script.py
sigmas/simulations/python/runRecipes.py
sigmas/simulations/python/run_recipes.py
sigmas/simulations/python/simulationDefinitions.py
sigmas/simulations/python/sources.py
sigmas/static/favicon.png
sigmas/static/main.js
sigmas/static/styles.css
sigmas/static/fonts/JetBrainsMono-Bold.woff2
sigmas/static/fonts/JetBrainsMono-Regular.woff2
sigmas/static/js9/astroem.js
sigmas/static/js9/astroemw.js
sigmas/static/js9/astroemw.wasm
sigmas/static/js9/favicon.ico
sigmas/static/js9/js9-allinone.css
sigmas/static/js9/js9-allinone.js
sigmas/static/js9/js9.css
sigmas/static/js9/js9.html
sigmas/static/js9/js9.js
sigmas/static/js9/js9.min.js
sigmas/static/js9/js9Electron.js
sigmas/static/js9/js9ElectronMainMenu.js
sigmas/static/js9/js9ElectronPreload.js
sigmas/static/js9/js9Helper.js
sigmas/static/js9/js9Msg.js
sigmas/static/js9/js9PostMessage.js
sigmas/static/js9/js9Prefs.json
sigmas/static/js9/js9Regions.js
sigmas/static/js9/js9plugins.js
sigmas/static/js9/js9prefs.js
sigmas/static/js9/js9support.css
sigmas/static/js9/js9support.js
sigmas/static/js9/js9support.min.js
sigmas/static/js9/js9support.txt
sigmas/static/js9/js9worker.js
sigmas/static/js9/css/dhtmlwindow.css
sigmas/static/js9/css/jquery.contextMenu-v2.8.0.css
sigmas/static/js9/css/jquery.contextMenu.css
sigmas/static/js9/css/spectrum.css
sigmas/static/js9/css/tabcontent.css
sigmas-0.1.2.dist-info/licenses/LICENSE
sigmas-0.1.2.dist-info/METADATA
sigmas-0.1.2.dist-info/WHEEL
sigmas-0.1.2.dist-info/entry_points.txt
sigmas-0.1.2.dist-info/top_level.txt
sigmas-0.1.2.dist-info/RECORD
