Metadata-Version: 2.4
Name: sigmas
Version: 0.1.2
Summary: Simulation Interface for Generating METIS Astronomical Spectra
Author-email: Benjamin Eisele <benjamin.eisele0101@gmail.com>
License-Expression: GPL-3.0-or-later
Classifier: Programming Language :: Python :: 3
Classifier: Operating System :: OS Independent
Requires-Python: >=3.10
License-File: LICENSE
Requires-Dist: flask
Requires-Dist: scopesim
Requires-Dist: scopesim_templates
Requires-Dist: astropy
Requires-Dist: numpy
Requires-Dist: click
Requires-Dist: sphinx
Requires-Dist: astrodonut
Dynamic: license-file
